{"fetched_at": "2026-07-10T00:00:00Z", "summary": {"symbol": "MU", "as_of": "2026-07-09T23:59:58.597Z", "market_open": false, "price": {"bid": 1002.27, "ask": 1002.5, "mid": 1002.385, "last": 1002.385, "last_update": "2026-07-09T23:59:58.597Z"}, "volatility": {"atm_iv": 106.98, "hv_20": 119.39, "hv_60": 104.37, "vrp": null, "skew_25d": null, "iv_term_structure": null}, "options_flow": {"total_call_oi": 1636533, "total_put_oi": 2160368, "total_call_volume": 44114, "total_put_volume": 61175, "pc_ratio_oi": 1.32, "pc_ratio_volume": 1.387, "active_expirations": 25}, "exposure": {"net_gex": 357096153, "net_dex": null, "net_vex": null, "net_chex": null, "gamma_flip": 996.093168753624, "call_wall": 1050, "put_wall": 1000, "max_pain": null, "highest_oi_strike": 600, "regime": "positive_gamma", "interpretation": {"gamma": "Dealers long gamma \u2014 moves dampened, mean reversion likely", "vanna": null, "charm": null}, "hedging_estimate": null, "zero_dte": null, "top_strikes": null, "oi_weighted_dte": 145.9}, "macro": {"vix": {"value": 15.84, "change": -1.06, "change_pct": -6.27, "as_of": "2026-07-09T20:15:01Z"}, "vvix": {"value": 88.78, "change": -2.6, "change_pct": -2.85, "as_of": "2026-07-09T20:15:01Z"}, "skew": {"value": 144.67, "change": -5.12, "change_pct": -3.42, "as_of": "2026-07-09T21:00:18Z"}, "spx": {"value": 7543.64, "change": 60.93, "change_pct": 0.81, "as_of": "2026-07-09T20:55:46Z"}, "move": {"value": 68.8935, "change": -3.52, "change_pct": -4.86, "as_of": "2026-07-09T20:38:45Z"}, "vix_term_structure": {"levels": {"vix9d": 12.5, "vix": 15.84, "vix3m": 18.99, "vix6m": 21.32}, "near_slope_pct": 26.72, "structure": "contango"}, "vix_futures": {"front_month": 18.99, "spot": 15.84, "spread": 3.15, "basis_pct": 19.89, "basis": "contango"}, "fear_and_greed": {"score": 47, "rating": "neutral"}}}}